CHANGES.rst
LICENSE.txt
MANIFEST.in
README.rst
setup.py
src/bst/__init__.py
src/bst.pygasus.session.egg-info/PKG-INFO
src/bst.pygasus.session.egg-info/SOURCES.txt
src/bst.pygasus.session.egg-info/dependency_links.txt
src/bst.pygasus.session.egg-info/entry_points.txt
src/bst.pygasus.session.egg-info/namespace_packages.txt
src/bst.pygasus.session.egg-info/not-zip-safe
src/bst.pygasus.session.egg-info/requires.txt
src/bst.pygasus.session.egg-info/top_level.txt
src/bst/pygasus/__init__.py
src/bst/pygasus/session/__init__.py
src/bst/pygasus/session/configure.zcml
src/bst/pygasus/session/cookies.py
src/bst/pygasus/session/interfaces.py
src/bst/pygasus/session/session.py